dnpy/__init__.py
dnpy/metadata/__init__.py
dnpy/metadata/il.py
dnpy/metadata/metadata.py
dnpy/metadata/opcodes.py
dnpy/metadata/operands.py
dnpy/metadata/signatures.py
dnpy/metadata/streams.py
dnpy/metadata/tokens.py
dnpy/model/__init__.py
dnpy/model/assembly.py
dnpy/model/members.py
dnpy/model/module.py
dnpy/model/types.py
dnpy/pe/__init__.py
dnpy/pe/pe_wrapper.py
dnpy/util/__init__.py
dnpy/util/buffers.py
dnpy/util/endian.py
dnpy/util/string_utils.py
dnpy-0.1.0.dist-info/licenses/LICENSE
dnpy-0.1.0.dist-info/METADATA
dnpy-0.1.0.dist-info/WHEEL
dnpy-0.1.0.dist-info/top_level.txt
dnpy-0.1.0.dist-info/RECORD
