Metadata-Version: 2.4
Name: dnpy
Version: 0.1.0
Summary: A library for reading and writing .NET modules
Author-email: "Utku Corbaci (rhotav)" <utku@rhotav.com>
Maintainer-email: "Utku Corbaci (rhotav)" <utku@rhotav.com>
License-Expression: MIT
Project-URL: Homepage, https://github.com/rhotav/dnpy
Project-URL: Repository, https://github.com/rhotav/dnpy
Project-URL: Documentation, https://github.com/rhotav/dnpy#readme
Project-URL: Bug Tracker, https://github.com/rhotav/dnpy/issues
Keywords: dotnet,.net,parser,disassembly
Classifier: Intended Audience :: Developers
Classifier: Operating System :: OS Independent
Classifier: Natural Language :: English
Classifier: Programming Language :: Python :: 3
Classifier: Topic :: Security
Requires-Python: >=3.10
License-File: LICENSE
Requires-Dist: pefile>=2024.8.26
Dynamic: license-file
